setup.py
py_build_server/__init__.py
py_build_server/main.py
py_build_server.egg-info/PKG-INFO
py_build_server.egg-info/SOURCES.txt
py_build_server.egg-info/dependency_links.txt
py_build_server.egg-info/entry_points.txt
py_build_server.egg-info/top_level.txt
py_build_server/config/__init__.py
py_build_server/config/config.py
py_build_server/lib/__init__.py
py_build_server/lib/api.py
py_build_server/lib/file_operations.py
py_build_server/lib/http_server_skeleton.py
py_build_server/lib/logger.py
py_build_server/lib/packaging.py
py_build_server/lib/python_daemon.py
py_build_server/lib/repo_extentions.py
py_build_server/lib/repository_api_clients.py
py_build_server/lib/repository_hooks.py
py_build_server/lib/test_runners.py
py_build_server/lib/updater.py
py_build_server/lib/web_server/__init__.py
py_build_server/lib/web_server/decorators.py
py_build_server/lib/web_server/html_objects.py
py_build_server/lib/web_server/builds/__init__.py
py_build_server/lib/web_server/builds/root.py