Metadata-Version: 1.1
Name: py-build-server
Version: 0.10.0
Summary: My build server i run on my home server to check for git repo tags, and push to pypi
Home-page: https://github.com/chestm007/py_build_server
Author: chestm007
Author-email: chestm007@hotmail.com
License: GPL3
Platform: UNKNOWN
Requires: click
Requires: gitpython
Requires: pyyaml
Requires: requests
Requires: cherrypy
